{
	"name": "Ender Pearl Fragment",
	"icon": "opolisutilities:textures/item/ender_pearl_fragment.png",

	"category": "opolisutilities:advanced_items",
	"sortnum": 6,
	"pages": [
		{
			"type": "text",
			"text": "Ender Pearl Fragments can drop from ender ore that spawns underground."
		},
		{
            "type": "spotlight",
            "item": "opolisutilities:ender_ore",
            "text": "Ender Ore"
        },
        {
            "type": "spotlight",
            "item": "opolisutilities:deepslate_ender_ore",
            "text": "Deepslate Ender Ore"
        },
		{
			"type": "crafting",
			"recipe": "opolisutilities:ender_pearl_from_ender_pearl_fragments",
			"text": "Used to make Ender Pearls."
		}
	]
}